discord_oauth2/__init__.py
discord_oauth2-0.2.dist-info/LICENSE
discord_oauth2-0.2.dist-info/METADATA
discord_oauth2-0.2.dist-info/WHEEL
discord_oauth2-0.2.dist-info/top_level.txt
discord_oauth2-0.2.dist-info/RECORD
