Metadata-Version: 2.1
Name: discord-oauth2
Version: 0.2
Summary: A python library that uses discord's api for easy authentication for your website.
Home-page: https://github.com/paulablaza/discord-oauth2
Author: Paul Martin Ablaza
Author-email: ablazapaulmartin@protonail.com
License: MIT
Keywords: discord auth,discord oauht2,oauth2
Platform: UNKNOWN
Classifier: Development Status :: 3 - Alpha
Classifier: Intended Audience :: Developers
Classifier: License :: OSI Approved :: MIT License
Classifier: Programming Language :: Python :: 3
Classifier: Programming Language :: Python :: 3.7
Classifier: Programming Language :: Python :: 3.8
Classifier: Programming Language :: Python :: 3.9
License-File: LICENSE
Requires-Dist: requests
